{
	"miniprogramRoot": "miniprogram/",
	"cloudfunctionRoot": "cloudfunctions/",
	"setting": {
		"urlCheck": true,
		"es6": true,
		"postcss": true,
		"minified": true,
		"newFeature": true,
		"enhance": true
	},
	"appid": "wx666aab010e97c51d",
	"projectname": "%E4%B8%80%E5%91%A8CP",
	"libVersion": "2.8.1",
	"simulatorType": "wechat",
	"simulatorPluginLibVersion": {},
	"cloudfunctionTemplateRoot": "cloudfunctionTemplate",
	"condition": {
		"search": {
			"current": -1,
			"list": []
		},
		"conversation": {
			"current": -1,
			"list": []
		},
		"plugin": {
			"current": -1,
			"list": []
		},
		"game": {
			"list": []
		},
		"miniprogram": {
			"current": 3,
			"list": [
				{
					"id": -1,
					"name": "db guide",
					"pathName": "pages/databaseGuide/databaseGuide",
					"query": ""
				},
				{
					"id": -1,
					"name": "pages/welcome/welcome",
					"pathName": "pages/welcome/welcome",
					"query": "",
					"scene": null
				},
				{
					"id": 2,
					"name": "pages/register2/register2",
					"pathName": "pages/register2/register2",
					"query": "",
					"scene": null
				},
				{
					"id": -1,
					"name": "email verify",
					"pathName": "pages/email_verify/email_verify",
					"query": "",
					"scene": null
				}
			]
		}
	}
}